[
	{
		"name": "$event",
		"order": 16384,
		"pvardefs": [

		],
		"lvardefs": [
			{
				"name": "lbFound",
				"order": 5,
				"type": "kBoolean",
				"subtype": 0,
				"sublen": 0
			},
			{
				"name": "lcMissing",
				"order": 6,
				"type": "kCharacter",
				"subtype": "kSimplechar",
				"sublen": 255
			},
			{
				"name": "lcResponse",
				"order": 4,
				"type": "kCharacter",
				"subtype": "kSimplechar",
				"sublen": 255
			},
			{
				"name": "lcSpecificColumns",
				"order": 2,
				"type": "kCharacter",
				"subtype": "kSimplechar",
				"sublen": 1000
			},
			{
				"name": "lcSTBcode",
				"order": 3,
				"type": "kCharacter",
				"subtype": "kSimplechar",
				"sublen": 100
			},
			{
				"name": "llTemp",
				"order": 1,
				"type": "kList",
				"subtype": "",
				"sublen": 0
			}
		]
	}
]
