{
	"ident": 1097,
	"order": 16,
	"objtype": "kEntry",
	"properties": {
		"align": "kLeftJst",
		"autofind": false,
		"calculated": true,
		"componentinfo": {

		},
		"dataname": "",
		"desgroup": 0,
		"deslock": false,
		"dupblanks": false,
		"fieldstyle": "reportMedium",
		"floating": false,
		"font": 1,
		"fontextra": 0,
		"fontsize": 12,
		"fontstyle": "kPlain",
		"formatmode": "kFormatCharacter",
		"formatstring": "",
		"height": -1,
		"horzextend": false,
		"horzslide": false,
		"left": 4.602,
		"lineno": 4,
		"lineoffset": 0.0,
		"linkaddress": "",
		"negbrackets": false,
		"nolineifempty": false,
		"noreload": false,
		"nosecifempty": false,
		"printontop": false,
		"readingordergrp": 0,
		"readingorderindex": 0,
		"showcommas": false,
		"shownulls": false,
		"text": {
			"type": 1,
			"calc": "pick(ilData.TP_SHUTTLE,'n/a','international','local')"
		},
		"textcolor": "kBlack",
		"tooltip": "",
		"totalmode": "kTmNone",
		"totalsifnoline": false,
		"userinfo": "",
		"vertextend": true,
		"visible": true,
		"width": 6.596,
		"zeroempty": false
	}
}
