{
	"classtype": "kTask",
	"omnisversion": "11.1",
	"omnisbuild": 111037255,
	"internalversion": 37,
	"superclass": "tkSuper",
	"tvardefs": [

	],
	"cvardefs": [

	],
	"ivardefs": [
		{
			"name": "ibSaveOnError",
			"order": 15,
			"type": "kBoolean",
			"subtype": 0,
			"sublen": 0,
			"initval": "kTrue"
		},
		{
			"name": "ibTempDir",
			"order": 23,
			"type": "kBoolean",
			"subtype": 0,
			"sublen": 0
		},
		{
			"name": "icAuthor",
			"order": 20,
			"type": "kCharacter",
			"subtype": "kSimplechar",
			"sublen": 100000000
		},
		{
			"name": "icCompletionMethod",
			"order": 12,
			"type": "kCharacter",
			"subtype": "kSimplechar",
			"sublen": 100000000
		},
		{
			"name": "icPDFid",
			"order": 18,
			"type": "kCharacter",
			"subtype": "kSimplechar",
			"sublen": 100000000
		},
		{
			"name": "icReportClass",
			"order": 17,
			"type": "kCharacter",
			"subtype": "kSimplechar",
			"sublen": 100000000
		},
		{
			"name": "icSubject",
			"order": 22,
			"type": "kCharacter",
			"subtype": "kSimplechar",
			"sublen": 100000000
		},
		{
			"name": "icTitle",
			"order": 21,
			"type": "kCharacter",
			"subtype": "kSimplechar",
			"sublen": 100000000
		},
		{
			"name": "inTimeout",
			"order": 27,
			"type": "kInteger",
			"subtype": "k32bitint",
			"sublen": 0
		},
		{
			"name": "irCallerParams",
			"order": 19,
			"type": "kRow",
			"subtype": "",
			"sublen": 0
		},
		{
			"name": "irefCaller",
			"order": 14,
			"type": "kItemref",
			"subtype": "",
			"sublen": 0
		},
		{
			"name": "irefReportClass",
			"order": 24,
			"type": "kItemref",
			"subtype": "",
			"sublen": 0
		},
		{
			"name": "irefReportInst",
			"order": 2,
			"type": "kItemref",
			"subtype": "",
			"sublen": 0
		},
		{
			"name": "irJobAttributes",
			"order": 1,
			"type": "kRow",
			"subtype": "",
			"sublen": 0
		},
		{
			"name": "irJobIdentification",
			"order": 3,
			"type": "kRow",
			"subtype": "",
			"sublen": 0
		},
		{
			"name": "irReportData",
			"order": 25,
			"type": "kRow",
			"subtype": "",
			"sublen": 0
		}
	],
	"properties": {
		"canremotedebugwhenlocked": false,
		"collectperformancedata": false,
		"componenticon": 0,
		"componentinfo": {

		},
		"componenttype": "kCompStoreHidden",
		"createdate": "2023-05-20 08:27:25",
		"desc": "",
		"editor": "",
		"editordata": "",
		"external": true,
		"issupercomponent": false,
		"moddate": "2023-06-04 20:13:42",
		"showascheckedout": false,
		"userinfo": "",
		"vcsrevision": 0,
		"version": ""
	}
}
