[
	{
		"name": "$construct",
		"order": 1,
		"clientexec": false,
		"pvardefs": [

		],
		"lvardefs": [
			{
				"name": "liColRef",
				"order": 3,
				"type": "kItemref",
				"subtype": "",
				"sublen": 0
			},
			{
				"name": "llConferences",
				"order": 2,
				"type": "kList",
				"subtype": "",
				"sublen": 0
			},
			{
				"name": "lrCurrentConference",
				"order": 1,
				"type": "kRow",
				"subtype": "",
				"sublen": 0
			}
		]
	},
	{
		"name": "$setTabs",
		"order": 2,
		"clientexec": false,
		"pvardefs": [

		],
		"lvardefs": [

		]
	},
	{
		"name": "$extendToolsMenu",
		"order": 3,
		"clientexec": false,
		"pvardefs": [

		],
		"lvardefs": [

		]
	},
	{
		"name": "$destruct",
		"order": 4,
		"clientexec": false,
		"pvardefs": [

		],
		"lvardefs": [

		]
	},
	{
		"name": "$behaviour",
		"order": 5,
		"clientexec": false,
		"pvardefs": [

		],
		"lvardefs": [

		]
	},
	{
		"name": "recordMembership",
		"order": 6,
		"clientexec": false,
		"pvardefs": [

		],
		"lvardefs": [
			{
				"name": "lbOK",
				"order": 3,
				"type": "kBoolean",
				"subtype": 0,
				"sublen": 0
			},
			{
				"name": "lcMessage",
				"order": 4,
				"type": "kCharacter",
				"subtype": "kSimplechar",
				"sublen": 255
			},
			{
				"name": "llPaid",
				"order": 1,
				"type": "kList",
				"subtype": "",
				"sublen": 0
			},
			{
				"name": "lrMember",
				"order": 2,
				"type": "kRow",
				"subtype": "",
				"sublen": 0
			}
		]
	},
	{
		"name": "handleMenuCall",
		"order": 7,
		"clientexec": true,
		"pvardefs": [
			{
				"name": "pIdent",
				"order": 1,
				"type": "kCharacter",
				"subtype": "kSimplechar",
				"sublen": 100000000,
				"param": 1
			}
		],
		"lvardefs": [
			{
				"name": "lbFound",
				"order": 2,
				"type": "kCharacter",
				"subtype": "kSimplechar",
				"sublen": 100000000
			}
		]
	},
	{
		"name": "$fetchDetails",
		"order": 8,
		"clientexec": false,
		"pvardefs": [

		],
		"lvardefs": [
			{
				"name": "lbFound",
				"order": 1,
				"type": "kBoolean",
				"subtype": 0,
				"sublen": 0
			}
		]
	},
	{
		"name": "DelegateLinkClicked",
		"order": 9,
		"clientexec": false,
		"pvardefs": [
			{
				"name": "pbOvertUserAction",
				"order": 3,
				"type": "kBoolean",
				"subtype": 0,
				"sublen": 0,
				"param": 1,
				"initval": "kFalse"
			},
			{
				"name": "pbShiftPressed",
				"order": 6,
				"type": "kBoolean",
				"subtype": 0,
				"sublen": 0,
				"param": 2,
				"initval": "kFalse"
			}
		],
		"lvardefs": [
			{
				"name": "lbOK",
				"order": 1,
				"type": "kBoolean",
				"subtype": 0,
				"sublen": 0
			},
			{
				"name": "lbPrimaryDeleted",
				"order": 5,
				"type": "kBoolean",
				"subtype": 0,
				"sublen": 0,
				"initval": "kFalse"
			},
			{
				"name": "lbUpdateDatabase",
				"order": 2,
				"type": "kBoolean",
				"subtype": 0,
				"sublen": 0,
				"initval": "kFalse"
			},
			{
				"name": "lnCurrentLine",
				"order": 7,
				"type": "kInteger",
				"subtype": "k32bitint",
				"sublen": 0
			},
			{
				"name": "lnSelected",
				"order": 4,
				"type": "kInteger",
				"subtype": "k32bitint",
				"sublen": 0
			}
		]
	},
	{
		"name": "PrepareAutomatedInvoice",
		"order": 10,
		"clientexec": false,
		"pvardefs": [

		],
		"lvardefs": [
			{
				"name": "lbProceed",
				"order": 8,
				"type": "kBoolean",
				"subtype": 0,
				"sublen": 0
			},
			{
				"name": "llList",
				"order": 1,
				"type": "kList",
				"subtype": "",
				"sublen": 0
			},
			{
				"name": "lrConference",
				"order": 6,
				"type": "kRow",
				"subtype": "",
				"sublen": 0
			},
			{
				"name": "lrCustLookup",
				"order": 2,
				"type": "kRow",
				"subtype": "",
				"sublen": 0
			},
			{
				"name": "lrDelegate",
				"order": 3,
				"type": "kRow",
				"subtype": "",
				"sublen": 0
			},
			{
				"name": "lrOrgLink",
				"order": 7,
				"type": "kRow",
				"subtype": "",
				"sublen": 0
			},
			{
				"name": "lrProduct",
				"order": 5,
				"type": "kRow",
				"subtype": "",
				"sublen": 0
			}
		]
	},
	{
		"name": "PopulateDetailRow",
		"order": 11,
		"clientexec": false,
		"pvardefs": [
			{
				"name": "prProduct",
				"order": 2,
				"type": "kRow",
				"subtype": "",
				"sublen": 0,
				"param": 1
			}
		],
		"lvardefs": [

		]
	},
	{
		"name": "$displayListClick",
		"order": 12,
		"clientexec": false,
		"pvardefs": [

		],
		"lvardefs": [

		]
	},
	{
		"name": "calculateTotals",
		"order": 13,
		"clientexec": false,
		"pvardefs": [

		],
		"lvardefs": [

		]
	}
]
