{
	"classtype": "kObjectclass",
	"omnisversion": "11.1",
	"omnisbuild": 111037255,
	"internalversion": 8,
	"designtaskname": "Startup_Task",
	"cvardefs": [

	],
	"ivardefs": [
		{
			"name": "icConfigFile",
			"order": 23,
			"type": "kCharacter",
			"subtype": "kSimplechar",
			"sublen": 1000
		}
	],
	"properties": {
		"canremotedebugwhenlocked": false,
		"collectperformancedata": false,
		"componenticon": 0,
		"componentinfo": {

		},
		"componenttype": "kCompStoreHidden",
		"createdate": "2017-10-27 11:20:30",
		"desc": "",
		"editor": "",
		"editordata": "",
		"external": true,
		"issupercomponent": false,
		"moddate": "2019-05-30 10:30:14",
		"selfcontained": false,
		"showascheckedout": false,
		"userinfo": "",
		"vcsrevision": 0,
		"version": "2"
	}
}
