{
	"ident": 1020,
	"order": 9,
	"objtype": "kComponent",
	"componentlib": "jsList",
	"componentctrl": "List Control",
	"properties": {
		"active": true,
		"alpha": 255,
		"ariadescribedby": "",
		"arialabel": "",
		"arialabelledby": "",
		"autoscroll": true,
		"backalpha": 0,
		"backcolor": "RGB(238,238,238)",
		"bordercolor": "kColorDefault",
		"borderradius": "0",
		"checkboxcolor": "kColorDefault",
		"componentinfo": {

		},
		"contextmenu": "",
		"cssclassname": "",
		"dataname": "ilRolePermissions",
		"dateformat": "kJSFormatNone",
		"dateformatcustom": "",
		"defaultdisabledappearance": false,
		"defaultinactiveappearance": true,
		"desgroup": 0,
		"designactive": true,
		"deslock": false,
		"disabledefaultcontextmenu": false,
		"disablesystemfocus": false,
		"dragmode": "kDragData",
		"dropmode": "kAcceptControl",
		"effect": "kJSborderPlain",
		"enabled": true,
		"entertodoubleclick": true,
		"evenrowcolor": "kColorDefault",
		"events": "evDrop,evClick",
		"extraspace": 0,
		"fieldstyle": "",
		"font": 1,
		"fontsize": 10,
		"fontstyle": "kPlain",
		"hiliteline": false,
		"horzscroll": false,
		"iconid": 0,
		"ischecklist": false,
		"keyboardchangesline": false,
		"linestyle": 1,
		"listcolumn": 9,
		"nexttabobject": "",
		"numberformat": "",
		"objlink": 65543,
		"pagerpage": 1,
		"pagesize": 0,
		"preventlayoutanimation": false,
		"removefromtaborder": false,
		"selectedlinecolor": "kColorDefault",
		"selectedlinesonly": false,
		"selectedlinetextcolor": "kColorDefault",
		"sidepanel": false,
		"sidepanelmode": "kSidePanelModeNone",
		"textcolor": "kColorDefault",
		"tooltip": "",
		"userinfo": "",
		"vertscroll": false,
		"visible": true
	},
	"layout": {
		"320": {
			"left": 8,
			"top": 48,
			"width": 184,
			"height": 184,
			"dragborder": false,
			"edgefloat": "kEFnone",
			"errortextpos": "kJSErrorTextPosUnder",
			"visible": true
		},
		"375": {
			"left": 8,
			"top": 48,
			"width": 200,
			"height": 160,
			"dragborder": false,
			"edgefloat": "kEFnone",
			"errortextpos": "kJSErrorTextPosUnder",
			"visible": true
		},
		"480": {
			"left": 8,
			"top": 56,
			"width": 144,
			"height": 456,
			"dragborder": false,
			"edgefloat": "kEFbottom",
			"errortextpos": "kJSErrorTextPosUnder",
			"visible": true
		},
		"667": {
			"left": 8,
			"top": 56,
			"width": 200,
			"height": 392,
			"dragborder": false,
			"edgefloat": "kEFbottom",
			"errortextpos": "kJSErrorTextPosUnder",
			"visible": true
		},
		"768": {
			"left": 8,
			"top": 56,
			"width": 216,
			"height": 304,
			"dragborder": false,
			"edgefloat": "kEFbottom",
			"errortextpos": "kJSErrorTextPosUnder",
			"visible": true
		},
		"1024": {
			"left": 8,
			"top": 48,
			"width": 264,
			"height": 328,
			"dragborder": false,
			"edgefloat": "kEFbottom",
			"errortextpos": "kJSErrorTextPosUnder",
			"visible": true
		},
		"1700": {
			"left": 8,
			"top": 56,
			"width": 264,
			"height": 320,
			"dragborder": false,
			"edgefloat": "kEFbottom",
			"errortextpos": "kJSErrorTextPosUnder",
			"visible": true
		}
	}
}
