{
	"ident": 1165,
	"order": 9,
	"objtype": "kComponent",
	"componentlib": "jsButton",
	"componentctrl": "Button Control",
	"properties": {
		"::vertical": false,
		"active": true,
		"align": "kCenterJst",
		"alpha": 255,
		"ariadescribedby": "",
		"arialabel": "",
		"arialabelledby": "",
		"bordercolor": "kColorDefault",
		"borderwidth": 1,
		"buttonalpha": 255,
		"buttonbackiconid": 0,
		"buttonborderradius": 4,
		"buttoncolor": "kColorDefault",
		"componentinfo": {

		},
		"contextmenu": "",
		"cssclassname": "",
		"defaultinactiveappearance": true,
		"desgroup": 0,
		"designactive": true,
		"deslock": false,
		"disabledefaultcontextmenu": false,
		"disablesystemfocus": false,
		"dropmode": "kAcceptNone",
		"events": "evClick",
		"fieldstyle": "",
		"font": 1,
		"fontsize": 10,
		"fontstyle": "kPlain",
		"horzpadding": 0,
		"iconid": "k16x16+3003",
		"icontextspacing": 4,
		"isflat": true,
		"nexttabobject": "",
		"objlink": 65567,
		"preventlayoutanimation": false,
		"removefromtaborder": false,
		"sidepanel": false,
		"sidepanelmode": "kSidePanelModeNone",
		"spliticonandtext": false,
		"text": "",
		"textbeforeicon": false,
		"textcolor": "kColorDefault",
		"textishtml": false,
		"tooltip": "",
		"userinfo": "",
		"vertalign": "kJstVertMiddle",
		"vertpadding": 4,
		"visible": true
	},
	"screensizes": [
		{
			"name": "kSSZDesktop",
			"left": 296,
			"top": 392,
			"width": 25,
			"height": 25,
			"edgefloat": "kEFnone",
			"dragborder": false,
			"errortextpos": "kJSErrorTextPosUnder"
		}
	]
}
