{
	"classtype": "kRemoteForm",
	"omnisversion": "11.1",
	"omnisbuild": 111037255,
	"internalversion": 31,
	"superclass": "infra.rjsInfraSuper",
	"designtaskname": "rtBusinessApp",
	"nextident": 1015,
	"lastgroupident": 0,
	"cvardefs": [
		{
			"name": "clLabels",
			"order": 4,
			"type": "kList",
			"subtype": "",
			"sublen": 0
		},
		{
			"name": "cnPageArrangements",
			"order": 5,
			"type": "kInteger",
			"subtype": "kShortint",
			"sublen": 0,
			"initval": "5"
		},
		{
			"name": "cnPagePriceNow",
			"order": 9,
			"type": "kInteger",
			"subtype": "kShortint",
			"sublen": 0,
			"initval": "8"
		},
		{
			"name": "cnPagePriceSchedule",
			"order": 10,
			"type": "kInteger",
			"subtype": "kShortint",
			"sublen": 0,
			"initval": "9"
		},
		{
			"name": "cnPagePricing",
			"order": 8,
			"type": "kInteger",
			"subtype": "kShortint",
			"sublen": 0,
			"initval": "7"
		},
		{
			"name": "cnPageSpeakers",
			"order": 1,
			"type": "kInteger",
			"subtype": "kShortint",
			"sublen": 0,
			"initval": "1"
		},
		{
			"name": "cnPageSubmissions",
			"order": 7,
			"type": "kInteger",
			"subtype": "kShortint",
			"sublen": 0,
			"initval": "6"
		},
		{
			"name": "cnPageTopics1",
			"order": 2,
			"type": "kInteger",
			"subtype": "kShortint",
			"sublen": 0,
			"initval": "3"
		},
		{
			"name": "cnPageTopics2",
			"order": 3,
			"type": "kInteger",
			"subtype": "kShortint",
			"sublen": 0,
			"initval": "4"
		},
		{
			"name": "cnPageVenueInfo",
			"order": 6,
			"type": "kInteger",
			"subtype": "kShortint",
			"sublen": 0,
			"initval": "2"
		}
	],
	"ivardefs": [
		{
			"name": "inCurrentTab",
			"order": 1,
			"type": "kInteger",
			"subtype": "kShortint",
			"sublen": 0
		},
		{
			"name": "inTabCount",
			"order": 3,
			"type": "kInteger",
			"subtype": "k32bitint",
			"sublen": 0
		}
	],
	"properties": {
		"aligntogrid": false,
		"alpha": 255,
		"alwaysenabledobject": "",
		"animatelayouttransitions": false,
		"backalpha": 255,
		"backcolor": "RGB(255,255,255)",
		"backpattern": 0,
		"cancelkeyobject": "",
		"canremotedebugwhenlocked": false,
		"collectperformancedata": false,
		"componenticon": 0,
		"componentinfo": {

		},
		"componenttype": "kCompStoreHidden",
		"contextmenu": "",
		"createdate": "2024-06-27 14:37:12",
		"currentlayoutbreakpoint": 1024,
		"defaultappearance": "kAppearanceiOS",
		"desc": "UI container",
		"designguides": "",
		"designshowmobiletitle": true,
		"disabledefaultcontextmenu": false,
		"editor": "",
		"editordata": "",
		"events": "evScreenOrientationChanged,evLayoutChanged",
		"external": true,
		"forecolor": "RGB(255,255,255)",
		"horzgrid": 8,
		"horzscroll": false,
		"inheritedorder": 1,
		"issupercomponent": false,
		"layoutbreakpoints": "320,375,480,667,768,1024,1700",
		"layouttype": "kLayoutTypeResponsive",
		"left": 401,
		"menulineheight": 0,
		"moddate": "2025-05-07 10:51:43",
		"okkeyobject": "",
		"serverlessclient": false,
		"showascheckedout": false,
		"showgrid": false,
		"sizetogrid": false,
		"startfield": 0,
		"title": {
			"type": 0,
			"calc": "New remote form"
		},
		"top": 13,
		"userinfo": "",
		"vcsrevision": 0,
		"version": "",
		"vertgrid": 8,
		"vertscroll": false
	},
	"layout": {
		"width": 1450,
		"height": 1036,
		"320": {
			"height": 0,
			"padding": 2
		},
		"375": {
			"height": 0,
			"padding": 2
		},
		"480": {
			"height": 0,
			"padding": 2
		},
		"667": {
			"height": 0,
			"padding": 2
		},
		"768": {
			"height": 0,
			"padding": 2
		},
		"1024": {
			"height": 0,
			"padding": 2
		},
		"1700": {
			"height": 0,
			"padding": 2
		}
	}
}
